Metadata-Version: 2.1
Name: telegen
Version: 1.0.8
Summary: A CLI tool that generates code by parsing the Telegram Bot API page
Home-page: https://gitlab.com/strychnide/telegen
Author: Alessandro Cerruti
Author-email: strychnide@protonmail.com
License: UNKNOWN
Project-URL: Documentation, https://strychnide.gitlab.io/telegen
Project-URL: Issues, https://gitlab.com/strychnide/telegen/-/issues
Project-URL: Source, https://gitlab.com/strychnide/telegen
Platform: UNKNOWN
Classifier: Environment :: Console
Classifier: Intended Audience :: Developers
Classifier: License :: OSI Approved :: MIT License
Classifier: Operating System :: OS Independent
Classifier: Programming Language :: Python :: 3.8
Classifier: Topic :: Software Development :: Code Generators
Requires-Python: >=3.8
Requires-Dist: lxml
Provides-Extra: doc
Requires-Dist: sphinx ; extra == 'doc'
Requires-Dist: sphinx-rtd-theme ; extra == 'doc'
